examples/quickstart.py
fusionml/__init__.py
fusionml/tensor.py
fusionml/tensor_old.py
fusionml/_metal/__init__.py
fusionml/_metal/engine.py
fusionml/_metal/fast_backend.py
fusionml/_metal/hybrid_backend.py
fusionml/_metal/lazy_backend.py
fusionml/_metal/mps_backend.py
fusionml/_metal/optimized_ops.py
fusionml/_metal/parallel_tiled.py
fusionml/autograd/__init__.py
fusionml/autograd/grad.py
fusionml/functional/__init__.py
fusionml/nn/__init__.py
fusionml/nn/functional.py
fusionml/nn/module.py
fusionml/optim/__init__.py
fusionml/optim/optimizer.py
fusionml-0.2.0.dist-info/METADATA
fusionml-0.2.0.dist-info/WHEEL
fusionml-0.2.0.dist-info/top_level.txt
fusionml-0.2.0.dist-info/RECORD
