Metadata-Version: 2.4
Name: fusionml
Version: 0.2.0
Summary: High-Performance ML Framework for Apple Silicon
Home-page: https://github.com/yourname/fusionml
Author: Om Mohite
Author-email: Om Mohite <om.mohite@vit.edu.in>
License: MIT
Requires-Python: >=3.8
Requires-Dist: numpy>=1.20.0
Provides-Extra: metal
Requires-Dist: pyobjc-framework-Metal>=9.0; extra == "metal"
Provides-Extra: dev
Requires-Dist: pytest; extra == "dev"
Requires-Dist: black; extra == "dev"
Requires-Dist: mypy; extra == "dev"
Dynamic: author
Dynamic: home-page
Dynamic: requires-python
